{"is_source_file": true, "format": "JavaScript (React JSX)", "description": "This file defines a React functional component 'Card' used for rendering a styled card UI element with optional header and actions.", "external_files": ["react"], "external_methods": [], "published": ["Card"], "classes": [], "methods": [{"name": "Card({ title, subtitle, children, actions })", "description": "React functional component rendering a styled card with optional title, subtitle, children, and actions.", "scope": "", "scopeKind": ""}], "calls": ["React"], "search-terms": ["Card component", "React functional component", "UI card", "card header", "card actions", "React JSX"], "state": 2, "file_id": 75, "knowledge_revision": 314, "git_revision": "d7094c8bb3d5eeb9c23cb2ddab9b21d37ee8dfc5", "ctags": [{"_type": "tag", "name": "Card", "path": "/home/kavia/workspace/code-generation/roadrescue-quickassist-platform-41193-41202/frontend_user_website/src/components/ui/Card.js", "pattern": "/^export function Card({ title, subtitle, children, actions }) {$/", "language": "JavaScript", "kind": "function", "signature": "({ title, subtitle, children, actions })"}], "hash": "f02d552c067b6a39a408d481b61061e4", "format-version": 4, "code-base-name": "frontend_user_website", "filename": "frontend_user_website/src/components/ui/Card.js", "revision_history": [{"314": "d7094c8bb3d5eeb9c23cb2ddab9b21d37ee8dfc5"}]}